{
    "servicios" : [
        {
            "id" : 1,
            "img" : "icon-front.png",
            "titulo" : "Front end",
            "descripcion" : "Javascript/Github",
            "descripcion2" : "Booststrap/Gulp",
            "descripcion3" : "CSS3/SASS/LESS",
            "descripcion4" : "HTML5"
        },
        {
            "id" : 2,
            "img" : "icon-skill.png",
            "titulo" : "Habilidades Blandas",
            "descripcion" : "Trabajo en equipo",
            "descripcion2" : "Organización",
            "descripcion3" : "Planificación",
            "descripcion4" : "Respeto"
        },
        {
            "id" : 3,
            "img" : "icon-others.png",
            "titulo" : "Otros",
            "descripcion" : "Adobe Illustrator",
            "descripcion2" : "Adobe XD/Figma",
            "descripcion3" : "FileZilla",
            "descripcion4" : "Awscli"
        }
    ]
}